pyqt_explanation_balloon/__init__.py
pyqt_explanation_balloon/explanationBalloon.py
pyqt_explanation_balloon/ico/__init__.py
pyqt_explanation_balloon/ico/close.svg
pyqt_explanation_balloon-0.0.21.dist-info/LICENSE
pyqt_explanation_balloon-0.0.21.dist-info/METADATA
pyqt_explanation_balloon-0.0.21.dist-info/WHEEL
pyqt_explanation_balloon-0.0.21.dist-info/top_level.txt
pyqt_explanation_balloon-0.0.21.dist-info/RECORD
