Metadata-Version: 2.1
Name: pyqt-explanation-balloon
Version: 0.0.21
Summary: PyQt explanation balloon
Home-page: https://github.com/yjg30737/pyqt-explanation-balloon.git
Author: Jung Gyu Yoon
Author-email: yjg30737@gmail.com
License: MIT
License-File: LICENSE
Requires-Dist: PyQt5 (>=5.8)
